ufo_configs/__init__.py
ufo_configs/configs_manager.py
ufo_configs-2.0.0.dist-info/LICENSE
ufo_configs-2.0.0.dist-info/METADATA
ufo_configs-2.0.0.dist-info/WHEEL
ufo_configs-2.0.0.dist-info/top_level.txt
ufo_configs-2.0.0.dist-info/RECORD
