Metadata-Version: 2.1
Name: ufo-configs
Version: 2.0.0
Summary: A bespoke configs manager
Home-page: https://github.com/tomhosker/ufo_configs
Author: Tom Hosker
Author-email: tomdothosker@gmail.com
License: MIT
Platform: UNKNOWN
License-File: LICENSE
